chatai/__init__.py
chatai/chatai.py
chatai-0.0.1.dist-info/LICENSE
chatai-0.0.1.dist-info/METADATA
chatai-0.0.1.dist-info/WHEEL
chatai-0.0.1.dist-info/top_level.txt
chatai-0.0.1.dist-info/RECORD
