Metadata-Version: 2.1
Name: chatai
Version: 0.0.1
Summary: ChatAI is a Python package for creating chatbot apps with easy integration of NLP and ML capabilities, allowing it to understand and respond to user input in an intelligent and natural way.
Home-page: https://acnsoft.net/chatai
Author: AcnSoft
Author-email: info@acnsoft.net
Classifier: Programming Language :: Python :: 3
Classifier: License :: OSI Approved :: MIT License
Classifier: Operating System :: OS Independent
License-File: LICENSE
